convert_pdftodocx/__init__.py
convert_pdftodocx/convert_pdf2docx.py
convert_pdftodocx-0.0.1.dist-info/METADATA
convert_pdftodocx-0.0.1.dist-info/WHEEL
convert_pdftodocx-0.0.1.dist-info/top_level.txt
convert_pdftodocx-0.0.1.dist-info/RECORD
